kama/__init__.py
kama/acl.py
kama/client.py
kama/context.py
kama/database.py
kama/env.py
kama/kama_pb2.py
kama/kama_pb2_grpc.py
kama/log.py
kama/server.py
kama/shell.py
kama-1.3.1.dist-info/METADATA
kama-1.3.1.dist-info/RECORD
kama-1.3.1.dist-info/WHEEL
kama-1.3.1.dist-info/entry_points.txt
kama-1.3.1.dist-info/top_level.txt
