Metadata-Version: 2.1
Name: kama
Version: 1.3.1
Summary: A truth database
Home-page: https://kama.sh/
Author: Jeremy Grosser
Author-email: jeremy@oaklabs.is
License: Apache-2.0
Platform: UNKNOWN
Classifier: Development Status :: 3 - Alpha
Classifier: License :: OSI Approved :: Apache Software License
Requires-Dist: grpcio (==1.14.1)
